sse.py
newming_mcp_server-0.1.1.dist-info/METADATA
newming_mcp_server-0.1.1.dist-info/WHEEL
newming_mcp_server-0.1.1.dist-info/top_level.txt
newming_mcp_server-0.1.1.dist-info/RECORD
