Metadata-Version: 2.4
Name: newming-mcp-server
Version: 0.1.1
Summary: 뉴밍의 MCP 서버입니다.
Author: Newming
Requires-Python: >=3.8
Requires-Dist: requests>=2.31.0
Requires-Dist: fastmcp>=1.0.0
Dynamic: author
Dynamic: requires-python
